primenumbers/__init__.py
primenumbers/prime.py
primenumbercheck-0.0.1.dist-info/LICENSE
primenumbercheck-0.0.1.dist-info/METADATA
primenumbercheck-0.0.1.dist-info/WHEEL
primenumbercheck-0.0.1.dist-info/top_level.txt
primenumbercheck-0.0.1.dist-info/RECORD
